{
    "_id": "62df97efef6557f862ed45b2",
    "labels": [],
    "tags": [],
    "email": "ynzvn661@testusers.com",
    "firstName": "Test1ynzvn66",
    "lastName": "User1ynzvn66",
    "password": "$2b$10$fQ6KIa0OHjPm7qk7LW/XKeJXG5zk.Ha/njn.VkC4ZO7BVbLqRXPzi",
    "roles": [],
    "verificationToken": "12175beebf61e36e25440214c49a303eda0461210e8f6c76fedb35e5fcff184b",
    "createdAt": "2022-07-26T07:29:51.269Z",
    "updatedAt": "2022-07-26T07:29:51.272Z",
    "__v": 0,
    "createdBy": "62df97efef6557f862ed45b2"
}